config/config_loader.py
config/data_config.py
data/__init__.py
encoding_objects/__init__.py
encoding_objects/cart_2d_enc_obj.py
gradops/finite_diff_torch.py
gradops/gradops_torch.py
networks/__init__.py
networks/denoising_pdhg_net.py
networks/mri_pdhg_net.py
networks/unet.py
networks/unet_2d.py
pdhg/mri_pdhg.py
pdhg/pdhg.py
pdhg/scalar_searcher.py
scripts/epoch.py
scripts/logger.py
scripts/unet_loader.py
utils/__init__.py
utils/makepath.py
utils/mask_funcs.py
utils/metrics.py
utils/noise_functions.py
utils/results.py
utils/search.py
utils/visualize.py
utils/warmup.py
reglearn-0.0.0.dist-info/LICENSE
reglearn-0.0.0.dist-info/METADATA
reglearn-0.0.0.dist-info/WHEEL
reglearn-0.0.0.dist-info/top_level.txt
reglearn-0.0.0.dist-info/RECORD
